core/smashconfig.py
smashconfig-1.0.0.dist-info/licenses/LICENSE
smashconfig-1.0.0.dist-info/METADATA
smashconfig-1.0.0.dist-info/WHEEL
smashconfig-1.0.0.dist-info/top_level.txt
smashconfig-1.0.0.dist-info/RECORD
