Metadata-Version: 2.4
Name: smashconfig
Version: 1.0.0
Summary: Creates config file for configparser module to use within the user's home config dir
Author-email: Laurence Lawlor <laurencelawlor@gmail.com>
License-Expression: MIT
Classifier: Programming Language :: Python :: 3
Classifier: Operating System :: OS Independent
Requires-Python: >=3.9
License-File: LICENSE
Dynamic: license-file
